fluent_async/__init__.py
fluent_async-0.1.2.dist-info/LICENSE
fluent_async-0.1.2.dist-info/METADATA
fluent_async-0.1.2.dist-info/WHEEL
fluent_async-0.1.2.dist-info/RECORD
